FailUrlRepush/__init__.py
FailUrlRepush/gears.py
FailUrlRepush/pushfailurls.py
pushurls-0.0.3.dist-info/LICENSE
pushurls-0.0.3.dist-info/METADATA
pushurls-0.0.3.dist-info/WHEEL
pushurls-0.0.3.dist-info/entry_points.txt
pushurls-0.0.3.dist-info/top_level.txt
pushurls-0.0.3.dist-info/RECORD
